{
    "os": "Linux-5.4.0-146-generic-x86_64-with-glibc2.35",
    "python": "3.10.0",
    "heartbeatAt": "2023-05-19T01:59:47.694227",
    "startedAt": "2023-05-19T01:59:46.806555",
    "docker": null,
    "cuda": null,
    "args": [],
    "state": "running",
    "program": "/root/src/pgx/pgx/workspace/backgammon_trainig/ppo.py",
    "codePath": "workspace/backgammon_trainig/ppo.py",
    "git": {
        "remote": "https://github.com/sotetsuk/pgx.git",
        "commit": "d7ff2e95fe2d96abef84dfa2250c148e9146a2e5"
    },
    "email": "kyoudai.630@gmail.com",
    "root": "/root/src/pgx/pgx",
    "host": "3480689c7656",
    "username": "root",
    "executable": "/root/.pyenv/versions/3.10.0/bin/python",
    "cpu_count": 24,
    "cpu_count_logical": 48,
    "cpu_freq": {
        "current": 1677.0083333333332,
        "min": 1200.0,
        "max": 2900.0
    },
    "cpu_freq_per_core": [
        {
            "current": 2523.121,
            "min": 1200.0,
            "max": 2900.0
        },
        {
            "current": 1200.285,
            "min": 1200.0,
            "max": 2900.0
        },
        {
            "current": 1771.871,
            "min": 1200.0,
            "max": 2900.0
        },
        {
            "current": 1201.307,
            "min": 1200.0,
            "max": 2900.0
        },
        {
            "current": 2540.258,
            "min": 1200.0,
            "max": 2900.0
        },
        {
            "current": 1780.49,
            "min": 1200.0,
            "max": 2900.0
        },
        {
            "current": 1395.716,
            "min": 1200.0,
            "max": 2900.0
        },
        {
            "current": 1199.933,
            "min": 1200.0,
            "max": 2900.0
        },
        {
            "current": 1202.202,
            "min": 1200.0,
            "max": 2900.0
        },
        {
            "current": 1200.385,
            "min": 1200.0,
            "max": 2900.0
        },
        {
            "current": 2540.178,
            "min": 1200.0,
            "max": 2900.0
        },
        {
            "current": 1201.044,
            "min": 1200.0,
            "max": 2900.0
        },
        {
            "current": 2582.979,
            "min": 1200.0,
            "max": 2900.0
        },
        {
            "current": 1599.697,
            "min": 1200.0,
            "max": 2900.0
        },
        {
            "current": 1495.648,
            "min": 1200.0,
            "max": 2900.0
        },
        {
            "current": 1200.887,
            "min": 1200.0,
            "max": 2900.0
        },
        {
            "current": 1200.96,
            "min": 1200.0,
            "max": 2900.0
        },
        {
            "current": 1204.899,
            "min": 1200.0,
            "max": 2900.0
        },
        {
            "current": 2145.021,
            "min": 1200.0,
            "max": 2900.0
        },
        {
            "current": 2189.57,
            "min": 1200.0,
            "max": 2900.0
        },
        {
            "current": 1201.055,
            "min": 1200.0,
            "max": 2900.0
        },
        {
            "current": 1204.038,
            "min": 1200.0,
            "max": 2900.0
        },
        {
            "current": 1200.862,
            "min": 1200.0,
            "max": 2900.0
        },
        {
            "current": 2586.056,
            "min": 1200.0,
            "max": 2900.0
        },
        {
            "current": 2545.532,
            "min": 1200.0,
            "max": 2900.0
        },
        {
            "current": 1200.083,
            "min": 1200.0,
            "max": 2900.0
        },
        {
            "current": 1667.187,
            "min": 1200.0,
            "max": 2900.0
        },
        {
            "current": 1200.028,
            "min": 1200.0,
            "max": 2900.0
        },
        {
            "current": 2532.153,
            "min": 1200.0,
            "max": 2900.0
        },
        {
            "current": 1798.535,
            "min": 1200.0,
            "max": 2900.0
        },
        {
            "current": 1393.304,
            "min": 1200.0,
            "max": 2900.0
        },
        {
            "current": 1200.196,
            "min": 1200.0,
            "max": 2900.0
        },
        {
            "current": 1199.798,
            "min": 1200.0,
            "max": 2900.0
        },
        {
            "current": 1200.668,
            "min": 1200.0,
            "max": 2900.0
        },
        {
            "current": 2496.373,
            "min": 1200.0,
            "max": 2900.0
        },
        {
            "current": 1200.753,
            "min": 1200.0,
            "max": 2900.0
        },
        {
            "current": 2560.018,
            "min": 1200.0,
            "max": 2900.0
        },
        {
            "current": 2261.496,
            "min": 1200.0,
            "max": 2900.0
        },
        {
            "current": 1684.169,
            "min": 1200.0,
            "max": 2900.0
        },
        {
            "current": 1200.977,
            "min": 1200.0,
            "max": 2900.0
        },
        {
            "current": 1201.026,
            "min": 1200.0,
            "max": 2900.0
        },
        {
            "current": 1200.176,
            "min": 1200.0,
            "max": 2900.0
        },
        {
            "current": 2107.622,
            "min": 1200.0,
            "max": 2900.0
        },
        {
            "current": 2051.103,
            "min": 1200.0,
            "max": 2900.0
        },
        {
            "current": 1200.111,
            "min": 1200.0,
            "max": 2900.0
        },
        {
            "current": 1200.167,
            "min": 1200.0,
            "max": 2900.0
        },
        {
            "current": 1200.055,
            "min": 1200.0,
            "max": 2900.0
        },
        {
            "current": 2499.511,
            "min": 1200.0,
            "max": 2900.0
        }
    ],
    "disk": {
        "total": 207.51084899902344,
        "used": 34.99995422363281
    },
    "gpu": "NVIDIA GeForce GTX 1080 Ti",
    "gpu_count": 4,
    "gpu_devices": [
        {
            "name": "NVIDIA GeForce GTX 1080 Ti",
            "memory_total": 11811160064
        },
        {
            "name": "NVIDIA GeForce GTX 1080 Ti",
            "memory_total": 11811160064
        },
        {
            "name": "NVIDIA GeForce GTX 1080 Ti",
            "memory_total": 11811160064
        },
        {
            "name": "NVIDIA GeForce GTX 1080 Ti",
            "memory_total": 11811160064
        }
    ],
    "memory": {
        "total": 251.78957748413086
    }
}
